README.md
setup.py
wfsayhello/__init__.py
wfsayhello/functions.py
wfsayhello.egg-info/PKG-INFO
wfsayhello.egg-info/SOURCES.txt
wfsayhello.egg-info/dependency_links.txt
wfsayhello.egg-info/top_level.txt