Metadata-Version: 2.1
Name: wfsayhello
Version: 0.1.0
Summary: Webforce say hello package
Home-page: UNKNOWN
Author: Webforce
Author-email: ehoy@webforcehq.com
License: UNKNOWN
Platform: UNKNOWN
Classifier: Programming Language :: Python :: 3
Classifier: License :: OSI Approved :: MIT License
Classifier: Operating System :: OS Independent
Requires-Python: >=3.6
